odoo/addons/l10n_be_apb_tax/README.rst
odoo/addons/l10n_be_apb_tax/__init__.py
odoo/addons/l10n_be_apb_tax/__manifest__.py
odoo/addons/l10n_be_apb_tax/hooks.py
odoo/addons/l10n_be_apb_tax/data/account_account_template_data.xml
odoo/addons/l10n_be_apb_tax/data/account_fiscal_position_tax_template.xml
odoo/addons/l10n_be_apb_tax/data/account_tax_code_template.xml
odoo/addons/l10n_be_apb_tax/data/account_tax_group.xml
odoo/addons/l10n_be_apb_tax/data/account_tax_template_apb_data.xml
odoo/addons/l10n_be_apb_tax/i18n/l10n_be_apb_tax.pot
odoo/addons/l10n_be_apb_tax/readme/CONFIGURE.rst
odoo/addons/l10n_be_apb_tax/readme/CONTRIBUTORS.rst
odoo/addons/l10n_be_apb_tax/readme/DESCRIPTION.rst
odoo/addons/l10n_be_apb_tax/readme/INSTALL.rst
odoo/addons/l10n_be_apb_tax/readme/USAGE.rst
odoo/addons/l10n_be_apb_tax/static/description/icon.png
odoo/addons/l10n_be_apb_tax/static/description/index.html
odoo_addon_l10n_be_apb_tax-16.0.1.0.1.2.dist-info/METADATA
odoo_addon_l10n_be_apb_tax-16.0.1.0.1.2.dist-info/WHEEL
odoo_addon_l10n_be_apb_tax-16.0.1.0.1.2.dist-info/top_level.txt
odoo_addon_l10n_be_apb_tax-16.0.1.0.1.2.dist-info/RECORD
